[
  {
    "timestamp": "2025-05-29T20:29:24.257Z",
    "user": "aa",
    "action": "view",
    "itemId": "6838a68c0c750ca0a04da939"
  },
  {
    "timestamp": "2025-05-29T20:29:38.863Z",
    "user": "aa",
    "action": "view",
    "itemId": "6838a099e44e7d3e6f0daeb7"
  },
  {
    "timestamp": "2025-05-29T20:30:09.525Z",
    "user": "aa",
    "action": "view",
    "itemId": "23277342-3948-4890-bbd5-b27c2cad6720"
  },
  {
    "timestamp": "2025-05-29T20:30:37.850Z",
    "user": "aa",
    "action": "view",
    "itemId": "6838a099e44e7d3e6f0daeb7"
  },
  {
    "timestamp": "2025-05-30T21:17:34.681Z",
    "user": "aaaa",
    "action": "view",
    "itemId": "6838c2edfc6adb41cc868030"
  },
  {
    "timestamp": "2025-05-30T22:22:17.225Z",
    "user": "aaaa",
    "action": "view",
    "itemId": "683a21ccd268f9575d78d494"
  },
  {
    "timestamp": "2025-05-30T22:22:30.606Z",
    "user": "aaaa",
    "action": "view",
    "itemId": "6838c1e8cb34fe678334b99d"
  },
  {
    "timestamp": "2025-05-30T22:30:27.775Z",
    "user": "aaaa",
    "action": "view",
    "itemId": "6838c1e8cb34fe678334b99d"
  },
  {
    "timestamp": "2025-05-30T22:36:04.038Z",
    "user": "aaaa",
    "action": "view",
    "itemId": "6838c1e8cb34fe678334b99d"
  },
  {
    "timestamp": "2025-05-30T22:50:30.107Z",
    "user": "aaaa",
    "action": "view",
    "itemId": "6838c1e8cb34fe678334b99d"
  },
  {
    "timestamp": "2025-05-30T22:50:35.614Z",
    "user": "aaaa",
    "action": "view_comments",
    "itemId": "6838c1e8cb34fe678334b99d"
  },
  {
    "timestamp": "2025-05-31T00:21:11.580Z",
    "user": "aaaa",
    "action": "view_comments",
    "itemId": "6838c1e8cb34fe678334b99d"
  },
  {
    "timestamp": "2025-05-31T00:21:16.969Z",
    "user": "aaaa",
    "action": "download",
    "itemId": "683a21ccd268f9575d78d494"
  },
  {
    "timestamp": "2025-05-31T00:21:39.516Z",
    "user": "aaaa",
    "action": "download",
    "itemId": "683a21ccd268f9575d78d494"
  },
  {
    "timestamp": "2025-05-31T00:21:45.621Z",
    "user": "aaaa",
    "action": "download",
    "itemId": "683a21ccd268f9575d78d494"
  },
  {
    "timestamp": "2025-05-31T00:22:23.540Z",
    "user": "aaaa",
    "action": "download",
    "itemId": "683a21ccd268f9575d78d494"
  },
  {
    "timestamp": "2025-05-31T10:49:33.597Z",
    "user": "aaaa",
    "action": "download",
    "itemId": "683a21ccd268f9575d78d494"
  },
  {
    "timestamp": "2025-05-31T11:45:55.243Z",
    "user": "aaaa",
    "action": "download",
    "itemId": "683a21ccd268f9575d78d494"
  },
  {
    "timestamp": "2025-05-31T13:46:44.131Z",
    "user": "bb",
    "action": "download",
    "itemId": "683b07a5d37880d0a335f62c"
  }
]